sochdb/__init__.py
sochdb/database.py
sochdb/errors.py
sochdb/format.py
sochdb/grpc_client.py
sochdb/ipc_client.py
sochdb/namespace.py
sochdb/query.py
sochdb/queue.py
sochdb/sochdb_pb2.py
sochdb/sochdb_pb2_grpc.py
sochdb/sql_engine.py
sochdb/vector.py
sochdb/_bin/aarch64-apple-darwin/sochdb-bulk
sochdb/_bin/aarch64-apple-darwin/sochdb-grpc-server
sochdb/_bin/aarch64-apple-darwin/sochdb-server
sochdb/lib/aarch64-apple-darwin/libsochdb_index.dylib
sochdb/lib/aarch64-apple-darwin/libsochdb_storage.dylib
sochdb/memory/__init__.py
sochdb/memory/consolidation.py
sochdb/memory/extraction.py
sochdb/memory/isolation.py
sochdb/memory/retrieval.py
sochdb/proto/sochdb_pb2.py
sochdb/proto/sochdb_pb2_grpc.py
sochdb-0.4.9.dist-info/licenses/LICENSE
sochdb-0.4.9.dist-info/METADATA
sochdb-0.4.9.dist-info/WHEEL
sochdb-0.4.9.dist-info/entry_points.txt
sochdb-0.4.9.dist-info/top_level.txt
sochdb-0.4.9.dist-info/RECORD
