Metadata-Version: 2.4
Name: sochdb
Version: 0.4.9
Summary: SochDB is an AI-native database with token-optimized output, O(|path|) lookups, built-in vector search, and durable transactions.
Author-email: Sushanth Reddy Vanagala <sushanth@sochdb.dev>
Maintainer-email: Sushanth <sushanth@sochdb.dev>
License: Apache-2.0
Project-URL: Homepage, https://sochdb.dev
Project-URL: Repository, https://github.com/sochdb/sochdb-python-sdk
Project-URL: Documentation, https://sochdb.dev
Project-URL: Bug Tracker, https://github.com/sochdb/sochdb-python-sdk/issues
Keywords: database,llm,ai,vector-search,embedded,key-value,sochdb,context-retrieval,transactions
Classifier: Development Status :: 4 - Beta
Classifier: Intended Audience :: Developers
Classifier: License :: OSI Approved :: Apache Software License
Classifier: Programming Language :: Python :: 3
Classifier: Programming Language :: Python :: 3.9
Classifier: Programming Language :: Python :: 3.10
Classifier: Programming Language :: Python :: 3.11
Classifier: Programming Language :: Python :: 3.12
Classifier: Programming Language :: Python :: 3.13
Classifier: Programming Language :: Rust
Classifier: Topic :: Database
Classifier: Topic :: Database :: Database Engines/Servers
Classifier: Topic :: Scientific/Engineering :: Artificial Intelligence
Classifier: Operating System :: MacOS
Classifier: Operating System :: POSIX :: Linux
Classifier: Operating System :: Microsoft :: Windows
Requires-Python: >=3.9
License-File: LICENSE
Requires-Dist: numpy>=1.20
Requires-Dist: grpcio>=1.50.0
Requires-Dist: grpcio-tools>=1.50.0
Requires-Dist: protobuf>=4.0.0
Provides-Extra: analytics
Requires-Dist: posthog>=3.0.0; extra == "analytics"
Provides-Extra: dev
Requires-Dist: pytest>=7.0; extra == "dev"
Requires-Dist: pytest-cov>=4.0; extra == "dev"
Requires-Dist: faker>=18.0; extra == "dev"
Provides-Extra: all
Requires-Dist: posthog>=3.0.0; extra == "all"
Dynamic: license-file
